aio_lanraragi-0.1.15.dist-info/licenses/LICENSE
lanraragi/__init__.py
lanraragi/clients/__init__.py
lanraragi/clients/api_context.py
lanraragi/clients/client.py
lanraragi/clients/utils.py
lanraragi/clients/api_clients/__init__.py
lanraragi/clients/api_clients/archive.py
lanraragi/clients/api_clients/base.py
lanraragi/clients/api_clients/category.py
lanraragi/clients/api_clients/database.py
lanraragi/clients/api_clients/minion.py
lanraragi/clients/api_clients/misc.py
lanraragi/clients/api_clients/search.py
lanraragi/clients/api_clients/shinobu.py
lanraragi/clients/api_clients/tankoubon.py
lanraragi/clients/res_processors/__init__.py
lanraragi/clients/res_processors/archive.py
lanraragi/clients/res_processors/category.py
lanraragi/clients/res_processors/database.py
lanraragi/clients/res_processors/minion.py
lanraragi/clients/res_processors/misc.py
lanraragi/clients/res_processors/search.py
lanraragi/clients/res_processors/tankoubon.py
lanraragi/models/__init__.py
lanraragi/models/archive.py
lanraragi/models/base.py
lanraragi/models/category.py
lanraragi/models/database.py
lanraragi/models/generics.py
lanraragi/models/minion.py
lanraragi/models/misc.py
lanraragi/models/search.py
lanraragi/models/shinobu.py
lanraragi/models/tankoubon.py
aio_lanraragi-0.1.15.dist-info/METADATA
aio_lanraragi-0.1.15.dist-info/WHEEL
aio_lanraragi-0.1.15.dist-info/top_level.txt
aio_lanraragi-0.1.15.dist-info/RECORD
