Metadata-Version: 2.4
Name: aio-lanraragi
Version: 0.1.15
Summary: An asynchronous Python API client for LANraragi, written with aiohttp and pydantic for type validation.
Author: psilabs-dev
License: MIT License
Project-URL: Homepage, https://github.com/psilabs-dev/aio-lanraragi
Requires-Python: <=3.14,>=3.12
License-File: LICENSE
Requires-Dist: aiohttp
Requires-Dist: pydantic>=2.0.0
Provides-Extra: dev
Requires-Dist: build; extra == "dev"
Requires-Dist: pytest>=8.0.0; extra == "dev"
Requires-Dist: pytest-asyncio>=0.25.0; extra == "dev"
Requires-Dist: ruff; extra == "dev"
Requires-Dist: setuptools; extra == "dev"
Requires-Dist: tox; extra == "dev"
Requires-Dist: twine; extra == "dev"
Dynamic: license-file
